{
    "data_info": {
        "documentID": "J_FOOD_021398",
        "source": "도서",
        "writer": "파란달",
        "ISBN_ISNN": "978-89-8827-456-9",
        "version": "초판",
        "source_language": "ko",
        "translator": "파파고",
        "source_url": "디저트가 맛있는 스위트 카페",
        "collectedDate": "2023-11-03",
        "publishedDate": "2009-01-19",
        "domain": "음식점",
        "title": "MODERN29"
    },
    "text": "鳳陽面面事務所の入口に位置しているMODERN29(モダン29)カフェです。 （建物1階、メゾネットタイプ、2階のカフェです。 毎日お店で良い材料で直接作る様々なデザートとコーヒーが飲めるデザートカフェです。 毎日のデザートのご案内はインスタグラムでご確認いただけます。 (すべてのデザート、手作りシロップは店内で直接作ります。 ) - 営業時間:月曜日11:00~09:00月曜日~土曜日|日曜日12:00~06:00日曜日 - 帰り道:鳳陽面事務所の入口に位置しています。 ^^駐車は建物の前庭、隣ラインに平行駐車面事務所の駐車場、その他通行の邪魔にならない場所に駐車してください。 - - メニュー : アメリカノ1,4,000ワン/アインシュペノ,6,000ワン/チャモンエド(手作りシロップ),5,500ワン/タルギ・ラテ(手作りシロップ),5,000ワン/アメリカノ2 (酸味),4,000ワン/レモネード,5,500ワン/カプチノ,5,000ワン/カペラテ,5,000ワン/パニララテ,5,500ワン/カラメル・マキアト,5,500ワン/アボカドバナナ,6,000ワン/トマトフルーツジュース,5,500ワン/ペションフルツ・エイドゥ(手作りシロップ),5,000ワン/ヨニュラテ,5,000ワン/グリンティ・ラテ,5,000ワン/クキエンクリム,6,000ワン/ミントチョコフラッペ,6,000ワン/ブルベリ・ヨゴトゥ,6,000ワン/マンゴー・スムージー,6,000ワン/タルギ・スムディ,6,000ワン/コグマ・ラテ,5、000ウォン/ハイビスカスレッド、4,000ウォン/ユーズカー、4,000ウォン/ユーズカー、4,000ウォン。",
    "QA": [
        {
            "question": "MODERN29カフェはどこに位置していますか？",
            "answer": "MODERN29カフェは鳳陽面面事務所の入口に位置しています。"
        },
        {
            "question": "MODERN29カフェの営業時間は何時から何時までですか？",
            "answer": "MODERN29カフェの営業時間は月曜日から土曜日は11時から21時まで、日曜日は12時から18時までです。"
        },
        {
            "question": "MODERN29カフェのメニューにはどんなものがありますか？",
            "answer": "MODERN29カフェのメニューにはアメリカノ1,4,000ワン/アインシュペノ、ワン/チャモンエド(手作りシロップ)、ワン/タルギ・ラテ(手作りシロップ)、ワン/アメリカノ2 (酸味)、ワン/レモネード、ワン/カプチノ、ワン/カペラテ、ワン/パニララテ、ワン/カラメル・マキアト、ワン/アボカドバナナ、ワン/トマトフルーツジュース、ワン/ペションフルツ・エイドゥ(手作りシロップ)、ワン/ヨニュラテ、ワン/グリンティ・ラテ、ワン/クキエンクリム、ワン/ミントチョコフラッペ、ワン/ブルベリ・ヨゴトゥ、ワン/マンゴー・スムージー、ワン/タルギ・スムディ、ワン/コグマ・ラテ、ワン/ハイビスカスレッド、ワン/ユーズカーがあります。"
        },
        {
            "question": "MODERN29カフェの駐車場はありますか？",
            "answer": "MODERN29カフェの駐車場は建物の前庭、隣ラインに平行駐車面事務所の駐車場、その他通行の邪魔にならない場所に駐車してください。"
        }
    ],
    "word_Count": {
        "text": 533,
        "QA": 417
    }
}