{
    "data_info": {
        "documentID": "J_FOOD_094654",
        "source": "도서",
        "writer": "노애리",
        "ISBN_ISNN": "9788997686926",
        "version": "초판 1쇄",
        "source_language": "ko",
        "translator": "파파고",
        "source_url": "'한국인이 좋아하는 도시락'",
        "collectedDate": "2023-11-20",
        "publishedDate": "2018-03-05",
        "domain": "음식점",
        "title": "전라 · 광주 지역 술"
    },
    "text": "ナヌウリ大々ポマクゴルリ、無等山(ムドゥンサン)、コメのマッコルリ(濁り酒)、兵営焼酎、赤い進駐、ヤマブドウワイン、送話百日酒、ジャヒヒャングクファジュ、全州(チョンジュ)米マッコリ、全州(チョンジュ)このきつい酒、ジュクリョクコ珍島(チンド)、ホンジュチャムドンが、ハブの葉、お酒、チョンジジュ、が生マッコリ、チュソンジュ、海南(ヘナム)チンヤン主、ヘチャン、マッコリ、ファンジンイジュです。",
    "QA": [
        {
            "question": "ナヌウリ大々ポマクゴルリとは何ですか？",
            "answer": "ナヌウリ大々ポマクゴルリは、韓国の伝統的なお酒で、米を原料として作られます。"
        },
        {
            "question": "無等山(ムドゥンサン)とはどんな場所ですか？",
            "answer": "無等山(ムドゥンサン)は、韓国にある美しい山で、自然景観やハイキングコースで知られています。"
        },
        {
            "question": "コメのマッコルリ(濁り酒)はどのように作られますか？",
            "answer": "コメのマッコルリ(濁り酒)は、米を発酵させて作られるお酒で、独特の濁りが特徴です。"
        },
        {
            "question": "兵営焼酎とはどんなお酒ですか？",
            "answer": "兵営焼酎は、韓国で作られる強い焼酎の一種で、日本の焼酎とは異なる特徴があります。"
        },
        {
            "question": "赤い進駐とは何ですか？",
            "answer": "赤い進駐は、韓国で作られる赤い色のお酒で、独特の味と香りがあります。"
        },
        {
            "question": "ヤマブドウワインとはどのようなワインですか？",
            "answer": "ヤマブドウワインは、韓国で栽培される山ブドウを使用して作られるワインです。"
        },
        {
            "question": "送話百日酒はどのようなお酒ですか？",
            "answer": "送話百日酒は、韓国で赤ちゃんの百日目を祝う際に飲まれるお酒で、祝福の意味が込められています。"
        },
        {
            "question": "ジャヒヒャングクファジュとは何ですか？",
            "answer": "ジャヒヒャングクファジュは、韓国の伝統的なお酒で、特別な機会や祝祭に飲まれることがあります。"
        },
        {
            "question": "全州(チョンジュ)米マッコリとはどんなお酒ですか？",
            "answer": "全州(チョンジュ)米マッコリは、韓国全州で作られる伝統的なマッコリで、その土地ならではの風味が楽しめます。"
        },
        {
            "question": "全州(チョンジュ)このきつい酒とはどのようなお酒ですか？",
            "answer": "全州(チョンジュ)このきつい酒は、韓国全州で作られる強いお酒で、アルコール度数が高いのが特徴です。"
        },
        {
            "question": "ジュクリョクコ珍島(チンド)とはどんな場所ですか？",
            "answer": "ジュクリョクコ珍島(チンド)は、韓国にある美しい島で、海岸や自然景観が魅力です。"
        },
        {
            "question": "ホンジュチャムドンが、ハブの葉、お酒、チョンジジュとは何ですか？",
            "answer": "ホンジュチャムドンが、ハブの葉、お酒、チョンジジュは、韓国の伝統的なお酒の一種で、特別な製法で作られます。"
        },
        {
            "question": "生マッコリとはどんなお酒ですか？",
            "answer": "生マッコリは、韓国で最も一般的なマッコリで、発酵が進んでいないため、さっぱりとした味わいです。"
        },
        {
            "question": "チュソンジュはどのようなお酒ですか？",
            "answer": "チュソンジュは、韓国で作られる伝統的なお酒で、米や麦などを原料として作られます。"
        },
        {
            "question": "海南(ヘナム)チンヤン主、ヘチャン、マッコリ、ファンジンイジュとは何ですか？",
            "answer": "海南(ヘナム)チンヤン主、ヘチャン、マッコリ、ファンジンイジュは、韓国の海南で作られる伝統的なお酒の一種で、独特の風味が楽しめます。"
        }
    ],
    "word_Count": {
        "text": 144,
        "QA": 739
    }
}