{
    "data_info": {
        "documentID": "J_FOOD_061399",
        "source": "온라인문서",
        "writer": "null",
        "ISBN_ISNN": "null",
        "version": "null",
        "source_language": "ko",
        "translator": "파파고",
        "source_url": "'https://www.10000recipe.com/recipe/6997605'",
        "collectedDate": "2023-11-22",
        "publishedDate": "2023-02-23",
        "domain": "음식점",
        "title": "김 장아찌 만드는 법 묵은 김 요리 일주일 반찬 김 반찬"
    },
    "text": "金おかずは冬にたくさん好んで食べるおかずと申します。今日はその中でも泊まった金にする金漬物の作り方法を教えてあげます。このおかずは簡単ながらもチャプチャルムハた味だと口ない時も良い選択と申します。金漬物を作るためには先に金を手入れしなければなりません。のりを水に漬けて柔らかくして、塩を振りかけて味を調節します。その後はタレを作らなければならないが、醤油、砂糖、おろしにんにく、ごま油、唐辛子の粉、ごまを混ぜて作ります。漬物桶に照りを侵犯させてスープをほとんど吸収させなければなりません。このように作られた漬物はご飯泥棒ともするが、おいしくて、一度食べた瞬間にご飯と金漬物を続けて食べたくなるのだ。調理時間は15分以内で、材料は在来のり、ゴマ、ジンカンジャン、コチュジャン、おろしたパー、センカンチョン、料理酒、水あめです。レシピはソースパンにコチュジャン大破を除いた材料を入れてぐつぐつ煮てくれます。固めた深ネギを入れてコチュジャンと胡麻を入れて、皆が混ぜてくれて完全に冷やしてくれます。在来のりは適当な大きさに切っているのに、私は6等分してくれました。金は4枚ずつ上げ、ソソを箸で塗ります。そして残りのソースは腫れてくださればいいです。",
    "QA": [
        {
            "question": "金漬物の作り方はどうですか？",
            "answer": "金漬物を作るためには、のりを水に漬けて柔らかくし、塩を振りかけて味を調節します。その後、タレを作り、醤油、砂糖、おろしにんにく、ごま油、唐辛子の粉、ごまを混ぜます。漬物桶にのりを敷き、タレをかけてスープをほとんど吸収させます。"
        },
        {
            "question": "金漬物の特徴や味はどうですか？",
            "answer": "金漬物は簡単ながらもチャプチャルムハた味で、口に合わない時にもおいしい選択肢です。ご飯との相性も良く、一度食べると続けて食べたくなるおかずです。"
        },
        {
            "question": "金漬物を作るために必要な材料は何ですか？",
            "answer": "金漬物を作るためには、在来のり、ゴマ、ジンカンジャン、コチュジャン、おろしたパー、センカンチョン、料理酒、水あめが必要です。"
        },
        {
            "question": "金漬物の作り方にはどのような手順がありますか？",
            "answer": "金漬物を作る手順は以下の通りです。1. のりを水に漬けて柔らかくする。2. 塩を振りかけて味を調節する。3. タレを作り、醤油、砂糖、おろしにんにく、ごま油、唐辛子の粉、ごまを混ぜる。4. 漬物桶にのりを敷き、タレをかけてスープをほとんど吸収させる。"
        },
        {
            "question": "金漬物を作るのにかかる時間はどのくらいですか？",
            "answer": "金漬物を作るのには15分以内の調理時間がかかります。"
        }
    ],
    "word_Count": {
        "text": 381,
        "QA": 361
    }
}