{
    "data_info": {
        "documentID": "J_FOOD_048884",
        "source": "온라인문서",
        "writer": "null",
        "ISBN_ISNN": "null",
        "version": "null",
        "source_language": "ko",
        "translator": "파파고",
        "source_url": "'https://www.10000recipe.com/recipe/6871814'",
        "collectedDate": "2023-11-22",
        "publishedDate": "2017-06-26",
        "domain": "음식점",
        "title": "비 오는날 뜨끈하게 닭개장"
    },
    "text": "雨の日にほかほか鶏のユッケジャン\\n\n雨がしとしとと降る日、考えが浮かびました。熱いお汁を食べたかったです。それで鍋に鶏を入れて水を注いだし、ながねぎ、にんにく、たまねぎ、月桂樹の葉、トンフチュを入れて煮てくれました。鶏は40-50分位煮りてくれば十分だと思いました。これまで材料を準備したが、玉ねぎは太く千切りにして長ネギは3-4cmに切っており、ワラビはまばらに切ってくれました。茹で上がった鶏は肉をむしって唐辛子の粉、ツナジングク、味付けの塩、おろしたニンニクを入れてもみもみ和えてくれました。鶏を救い出したスープに具はふるいで濾過してくれたし、ふるいにかけたスープに味付けした鶏肉を入れて一度作ってくれました。長ネギ、たまねぎ、ワラビを入れて沸いたら弱火に減らして煮てくれました。この時ソクムガンをしてくれたのに、粗塩を25スプーンくらい入れ、味わいながら口に合うようにソクムガンを調節しました。十分に作った鶏の開場を器に盛って胡椒を軽くかけて召し上がればいいです。コショウも好みに合わせて調節してください。",
    "QA": [
        {
            "question": "この料理はどのように作られますか？",
            "answer": "鍋に鶏を入れて水を注ぎ、ながねぎ、にんにく、たまねぎ、月桂樹の葉、トンフチュを入れて煮ます。鶏は40-50分煮れば十分です。茹で上がった鶏を唐辛子の粉、ツナジングク、塩、おろしたニンニクともみもみ和えます。スープに具はふるいで濾過し、味付けした鶏肉を入れて煮ます。最後に長ネギ、たまねぎ、ワラビを入れて沸いたら弱火に減らして煮ます。胡椒をかけて召し上がれます。"
        },
        {
            "question": "具材の切り方はどのようにしますか？",
            "answer": "玉ねぎは太く千切りに、長ネギは3-4cmに、ワラビはまばらに切ります。"
        },
        {
            "question": "鶏の開場はどのように盛り付けますか？",
            "answer": "鶏の開場を器に盛り付けて胡椒を軽くかけて召し上がってください。コショウも好みに合わせて調節してください。"
        },
        {
            "question": "ソクムガンとは何ですか？",
            "answer": "ソクムガンは塩の量を味わいながら調節することです。粗塩を25スプーンくらい入れ、口に合うように調整します。"
        },
        {
            "question": "鶏のユッケジャンはどのようなお料理ですか？",
            "answer": "鶏のユッケジャンは雨の日にほかほかと食べることのできる熱いお汁です。鶏肉や野菜を煮込んで作ります。"
        }
    ],
    "word_Count": {
        "text": 335,
        "QA": 332
    }
}