{
    "data_info": {
        "documentID": "J_FOOD_105723",
        "source": "온라인문서",
        "writer": "null",
        "ISBN_ISNN": "null",
        "version": "null",
        "source_language": "ko",
        "translator": "파파고",
        "source_url": "'https://www.bluer.co.kr/restaurants/32374",
        "collectedDate": "2023-10-16",
        "publishedDate": "2020-01-01",
        "domain": "음식점",
        "title": "화양연화"
    },
    "text": "花様年華住所:ソウル特別市江西区麻谷洞797-9マグナム797の基本説明:中華料理経歴20年を超えるシェフが料理するところ。香港の雰囲気は漂う中華料理店兼居酒屋だ。カジュアルな中華料理を披露して、こんがりに揚げた牛肉と各種野菜を一緒に炒めて出したモンゴリアンビーフが代表メニュー。表がこんがりして、中はしっとりしたメンボシャもお勧めだ。メニュー:ヤンジャンピの(万8千ウォン)、モンゴリアビーフ(万8千ウォン)、オヒャン枝エビ(8pcs二万2千ウォン)、メンボシャ(6pcs一万6千ウォン)、蹂躙機、四川風鶏手羽(各万1千ウォン)、醤油転覆の蒸し料理(三万二千ウォン)、クラゲつめたいあえもの&ジャンユク(万6千ウォン)価格帯:2~五万ウォン台の駐車可能可否:可能な行き方:営業時間:11:30~15:00(最後の注文14:30)/17:00~22:00(最後の注文21:00)特徴:お酒一杯しやすい、駐車可能。",
    "QA": [
        {
            "question": "この中華料理店はどこにありますか？",
            "answer": "この中華料理店はソウル特別市江西区麻谷洞797-9マグナム797にあります。"
        },
        {
            "question": "どのような料理が提供されていますか？",
            "answer": "この中華料理店では、ヤンジャンピの、モンゴリアビーフ、オヒャン枝エビ、メンボシャなどのメニューが提供されています。"
        },
        {
            "question": "この中華料理店の特徴は何ですか？",
            "answer": "この中華料理店は、お酒一杯しやすく、駐車も可能な特徴を持っています。"
        },
        {
            "question": "営業時間は何時から何時までですか？",
            "answer": "この中華料理店の営業時間は、11:30~15:00（最後の注文14:30）と17:00~22:00（最後の注文21:00）です。"
        },
        {
            "question": "この中華料理店への行き方を教えてください。",
            "answer": "この中華料理店への行き方は、ご要望に応じて案内いたします。"
        }
    ],
    "word_Count": {
        "text": 297,
        "QA": 228
    }
}