{
    "data_info": {
        "documentID": "J_FOOD_099135",
        "source": "온라인문서",
        "writer": "null",
        "ISBN_ISNN": "null",
        "version": "null",
        "source_language": "ko",
        "translator": "파파고",
        "source_url": "'https://www.10000recipe.com/recipe/1364640'",
        "collectedDate": "2023-11-22",
        "publishedDate": "2009-07-31",
        "domain": "음식점",
        "title": "취나물 된장무침"
    },
    "text": "味噌の香ばしい味がナムルの香りとよく合うシラヤマギク味噌和えは魅力的な韓国料理です。 材料としてはシラヤマギクと味噌が必要で、シラヤマギクはエゴマナムル、セバルナムルなど様々な種類が使えます。 味噌は唐辛子粉やコチュジャン、カタクチイワシの魚醤など様々な調味料と一緒に使用され、塩辛くなくても豊かな味を感じることができます。 シラヤマギクと味噌を一緒に炒め、ナムルの柔らかい食感と味噌の豊かな風味を一緒に楽しめます。 シラヤマギクの味噌和えはご飯と一緒に食べるにもよく、おかずとしてもよく合います。 韓国の伝統的な食べ物の一つで、多くの人が好んで食べる料理であり、健康にも良いです。 そしてシラヤマギクの栄養素も豊富で、さまざまな栄養を摂取できます。 そのため、韓国料理を楽しみたい人ならシラヤマギクの味噌和えを一度試してみることをおすすめします。 , 調理時間:15分以内、材料:シラヤマギク、味噌、刻みニンニク、ゴマ、エゴマ油、斜め、レシピ:鍋に水を入れて沸かしている間にナムルを整え、沸騰すると塩を大さじ1杯入れました そうしてこそ緑色が鮮明に光ります シラヤマギクを入れて木べらでかき混ぜながらまんべんなく煮込みました。茹でた臭みは取り出して冷水できれいに洗います。茎の間にある土まで除去できるように優しく洗ってください 味噌 2T きざみにんにく 12T 丸ごま 1T エゴマ油 1T 薄切り長ネギ 14本を入れてもみ和えてください。",
    "QA": [
        {
            "question": "シラヤマギク味噌和えはどんな韓国料理ですか？",
            "answer": "シラヤマギク味噌和えは、韓国料理の一つで、シラヤマギクと味噌を一緒に炒めて作る料理です。"
        },
        {
            "question": "シラヤマギク味噌和えにはどんな材料が必要ですか？",
            "answer": "シラヤマギク味噌和えには、シラヤマギクと味噌の他に、刻みニンニク、ゴマ、エゴマ油が必要です。"
        },
        {
            "question": "シラヤマギク味噌和えはどのように作るのですか？",
            "answer": "シラヤマギク味噌和えは、シラヤマギクを茹でて臭みを取り、冷水で洗った後、鍋で煮込みながら木べらでかき混ぜ、味噌、刻みニンニク、ゴマ、エゴマ油を加えて混ぜ合わせます。最後に薄切り長ネギを入れてもみ和えます。"
        },
        {
            "question": "シラヤマギク味噌和えはどんな食べ物とよく合いますか？",
            "answer": "シラヤマギク味噌和えはご飯とよく合います。また、おかずとしてもよく合います。"
        },
        {
            "question": "シラヤマギク味噌和えを食べると何か効果や効能がありますか？",
            "answer": "シラヤマギク味噌和えにはシラヤマギクの栄養素が豊富に含まれており、さまざまな栄養を摂取することができます。また、味噌には塩辛くなくても豊かな風味があり、健康にも良いとされています。"
        }
    ],
    "word_Count": {
        "text": 456,
        "QA": 325
    }
}