{
    "data_info": {
        "documentID": "J_FOOD_035410",
        "source": "도서",
        "writer": "노애리",
        "ISBN_ISNN": "9788997686926",
        "version": "초판 1쇄",
        "source_language": "ko",
        "translator": "파파고",
        "source_url": "'한국인이 좋아하는 도시락'",
        "collectedDate": "2023-11-20",
        "publishedDate": "2018-03-05",
        "domain": "음식점",
        "title": "오곡밥"
    },
    "text": "小正月に無事太平と豊作を祈り、多くの人と分けて食べる百家飯はもち米、黒豆、茶水、茶鳥、赤小豆の5種類の穀物を混ぜて炊いたご飯だ。もち米はきれいに洗ってふやかして水気を切った後、黒豆、茶こし、赤小豆も同様に洗って水気を切る。小豆はまず茹でたお湯で沸かして小豆水を捨て、また茹でたお湯で茹でて水気を切る。小豆湯に塩を入れて飯湯を作り、もち米に黒豆·茶水·赤小豆を入れて飯湯を注いで煮る。茶槽を入れて中火で下げて煮た後、米粒が広がったら弱火で下げて蒸らす。最後にご飯をヘラでまんべんなく混ぜた後、器に入れてサービングする。",
    "QA": [
        {
            "question": "百家飯は何種類の穀物を使って炊かれるのですか？",
            "answer": "百家飯はもち米、黒豆、茶水、茶鳥、赤小豆の5種類の穀物を混ぜて炊いたご飯です。"
        },
        {
            "question": "百家飯を炊く前に、もち米や黒豆、茶こし、赤小豆は何をする必要がありますか？",
            "answer": "もち米、黒豆、茶こし、赤小豆はきれいに洗って水気を切る必要があります。"
        },
        {
            "question": "小豆を煮る前に何をする必要がありますか？",
            "answer": "まず小豆を茹でたお湯で沸かして小豆水を捨て、再び茹でたお湯で茹でて水気を切る必要があります。"
        },
        {
            "question": "百家飯を炊く際に使う飯湯はどのように作るのですか？",
            "answer": "百家飯を炊く際には、小豆湯に塩を入れて飯湯を作ります。"
        },
        {
            "question": "百家飯を炊く際には、火力をどのように調整するのですか？",
            "answer": "茶槽を入れて中火で下げて煮た後、米粒が広がったら弱火で下げて蒸らします。"
        },
        {
            "question": "百家飯を食べる前に、最後に行う作業は何ですか？",
            "answer": "最後にご飯をヘラでまんべんなく混ぜた後、器に入れてサービングします。"
        }
    ],
    "word_Count": {
        "text": 189,
        "QA": 272
    }
}