{
    "data_info": {
        "documentID": "J_FOOD_109486",
        "source": "온라인문서",
        "writer": null,
        "ISBN_ISNN": null,
        "version": null,
        "source_language": "ko",
        "translator": "파파고",
        "source_url": "'https://www.10000recipe.com/recipe/6863699'",
        "collectedDate": "2023-11-22",
        "publishedDate": "2017-01-09",
        "domain": "음식점",
        "title": "카레향이 가득 카레두부부침 만들기"
    },
    "text": "カレーの香りたっぷりカレー·ジャム作り\\n\nあっさりした豆腐と香ばしいカレーが会う。豆腐は白に刺激もなく、まろやかな味を持っており、カレーは甘く芳しい味を自慢する。豆腐とカレーの出会いは完璧な調和を成す、カレーの豊富な味付けと豆腐のしっとりとした食感が調和して一口ごとに深い満足感を与える。豆腐とカレーはお互いを尊重し、それぞれの特徴を生かしながらも完璧な組合を叶えなければならない。淡泊な豆腐がカレーの風味を引き立てて、カレーは豆腐のまろやかな味を強調する。豆腐とカレーの調和を楽しみながら食べた瞬間ごとに食事がさらに豊かになる。あっさりした豆腐と香ばしいカレーの出会いはいつでも特別な組み合わせになるだろう。",
    "QA": [
        {
            "question": "カレー·ジャム作りの香りはどんな特徴がありますか？",
            "answer": "カレー·ジャムは香り高く、スパイシーで芳醇な香りが特徴です。"
        },
        {
            "question": "豆腐とカレーの組み合わせは、どのような味がしますか？",
            "answer": "豆腐とカレーの組み合わせは、豆腐のまろやかな味とカレーの甘く芳しい味が調和し、一口ごとに深い満足感を与えます。"
        },
        {
            "question": "豆腐とカレーの出会いによって食事はどのように豊かになりますか？",
            "answer": "豆腐とカレーの調和を楽しみながら食べることで、食事がさらに豊かになります。豆腐の淡泊な味がカレーの風味を引き立て、カレーは豆腐のまろやかな味を強調します。"
        }
    ],
    "word_Count": {
        "text": 224,
        "QA": 178
    }
}