{
    "data_info": {
        "documentID": "J_FOOD_000705",
        "source": "도서",
        "writer": "김정기",
        "ISBN_ISNN": "979-11-90641-80-7 (13980)",
        "version": "초판",
        "source_language": "ko",
        "translator": "파파고",
        "source_url": "52주 여행, 사계절 빛나는 전라도 430",
        "collectedDate": "2023-10-19",
        "publishedDate": "2022-08-05",
        "domain": "음식점",
        "title": "보성여관"
    },
    "text": "「太白山脈」の大河小説である「宝城旅館蜂」という作品は宝城旅館を中心に物語が展開される。 宝城旅館は作品の主要場所として登場し、ここで起きる事件が話を解いていく重要な役割を果たす。 作品の中で「慈愛病院」、「賢者の家」、「鉄橋」、「虹橋」など様々な場所も登場し、これを訪れる旅の楽しみもある。 しかし、伐橋旅行の真の魅力は断然「宝城旅館」にある。 ここは作品の中で描写される宝城旅館の実在地で、作品の世界をそのまま感じられる場所だ。 どこでもリラックスでき、伝統的な雰囲気と美しい自然景観が調和する場所として、多くの人に愛されている。 伐橋を旅行する人なら必ず立ち寄らなければならない場所だ。",
    "QA": [
        {
            "question": "宝城旅館はどのような場所ですか？",
            "answer": "宝城旅館は太白山脈の大河小説「宝城旅館蜂」の舞台となる実在の旅館です。ここは作品の中で描写される宝城旅館の実在地で、作品の世界をそのまま感じられる場所です。"
        },
        {
            "question": "宝城旅館で起きる事件はどのような役割を果たしますか？",
            "answer": "宝城旅館で起きる事件は物語の展開に重要な役割を果たします。作品の主要場所として登場し、話を解いていく上で欠かせない要素となっています。"
        },
        {
            "question": "宝城旅館以外にも作品中で登場する場所はありますか？",
            "answer": "はい、作品中では宝城旅館以外にも様々な場所が登場します。例えば「慈愛病院」、「賢者の家」、「鉄橋」、「虹橋」などがあります。これらの場所を訪れる旅も作品の楽しみの一つです。"
        },
        {
            "question": "宝城旅館の魅力は何ですか？",
            "answer": "宝城旅館の魅力はその雰囲気と自然景観にあります。どこでもリラックスでき、伝統的な雰囲気と美しい自然景観が調和しています。多くの人に愛される場所です。"
        },
        {
            "question": "伐橋を旅行する人にとって宝城旅館は必見ですか？",
            "answer": "はい、伐橋を旅行する人なら必ず宝城旅館を訪れるべき場所です。作品の世界をそのまま感じられ、リラックスできる素敵な場所です。ぜひ立ち寄ってみてください。"
        }
    ],
    "word_Count": {
        "text": 217,
        "QA": 354
    }
}