{
    "data_info": {
        "documentID": "J_FOOD_106365",
        "source": "온라인문서",
        "writer": null,
        "ISBN_ISNN": null,
        "version": null,
        "source_language": "ko",
        "translator": "파파고",
        "source_url": "'http://www.traveli.co.kr/read/contentsView/11388/0'",
        "collectedDate": "2019-11-01",
        "publishedDate": "2023-12-11",
        "domain": "음식점",
        "title": "정읍시, 내장산 단풍과 함께하는‘제2회 정읍쌍화차거리 축제’열린다"
    },
    "text": "井邑市、内蔵山紅葉とともに「第2回井邑双花茶通り祭り」が開かれる\n内蔵山紅葉と共にする「第2回井邑双花茶通り祭り」が11月2日と3日の2日間、井邑警察署民願駐車場で開かれる。 「2019~20井邑訪問の年」を迎えて行われる今回の祭りは井邑市が主催し、双和茶通り協議会(会長イ·グァンヨン)が主管する。 祭りは井邑双花茶通りを広報し、双花茶通り内の商店主と建物主、地域住民のネットワーク構築を通じた共同体強化のために用意された。 井邑双和茶通りは80年代から自生的に形成され、井邑税務署から井邑警察署まで続く約350mの喫茶店路地だ。 市はこの街の立ち遅れた物理的環境を改善し、住民主導の持続可能な路地に発展させ、全国初の双貨車特化通りを造成した。 今回のフェスティバルでは、双和車の試飲やフリーマーケットの運営など、様々な体験イベントが行われる。 また、綿菓子マジックショーと子供双花車モデル選抜大会、双花車健康ゴールデンベルなど多彩なイベントが用意される。 記念式は2日午後3時から行われ、午後4時からはJTV FM「チャン·ヘラの幸福発電所」特集公開放送で歌手パク·サンミンとチンジュ、イム·スジョン、真夏の祝賀公演が行われる。 3日には人気歌手のピョン·ジンソプとパク·ガンソン、自転車に乗った風景、チェ·スヨンなどが祭りの熱気を続ける予定だ。 ユ·ジンソプ市長は「多くの市民と観光客が来て、皆で暖かい双貨車で心を溶かして楽しい時間を共に分かち合うことを願う」と話した。 続いて「今回の祭りを通じて味と伝統が生きている井邑双和茶通りを外部に広く知らせ、これを通じて我が地域経済がより一層活性化されることを願う」と付け加えた。",
    "QA": [
        {
            "question": "祭りはいつ開催されますか？",
            "answer": "祭りは11月2日と3日の2日間、井邑警察署民願駐車場で開催されます。"
        },
        {
            "question": "祭りの主催者は誰ですか？",
            "answer": "祭りの主催者は井邑市です。"
        },
        {
            "question": "双和茶通りはどのように形成されましたか？",
            "answer": "双和茶通りは80年代から自生的に形成され、井邑税務署から井邑警察署まで続く約350mの喫茶店路地です。"
        },
        {
            "question": "祭りではどんな体験イベントが行われますか？",
            "answer": "祭りでは双和車の試飲やフリーマーケットの運営など、様々な体験イベントが行われます。"
        },
        {
            "question": "記念式はいつ行われますか？",
            "answer": "記念式は2日午後3時から行われます。"
        },
        {
            "question": "誰が祭りの特別公演を行いますか？",
            "answer": "JTV FM「チャン·ヘラの幸福発電所」特集公開放送で歌手パク·サンミンとチンジュ、イム·スジョン、真夏の祝賀公演が行われます。"
        },
        {
            "question": "市長は祭りについて何と話しましたか？",
            "answer": "ユ·ジンソプ市長は祭りについて多くの市民と観光客が来て、皆で暖かい双貨車で心を溶かして楽しい時間を共に分かち合うことを願い、地域経済がより一層活性化されることを願いました。"
        }
    ],
    "word_Count": {
        "text": 524,
        "QA": 308
    }
}