{
    "data_info": {
        "documentID": "J_FOOD_010556",
        "source": "온라인문서",
        "writer": "null",
        "ISBN_ISNN": "null",
        "version": "null",
        "source_language": "ko",
        "translator": "파파고",
        "source_url": "'https://www.bluer.co.kr/restaurants/31992",
        "collectedDate": "2023-10-16",
        "publishedDate": "2020-01-01",
        "domain": "음식점",
        "title": "두쓰멍"
    },
    "text": "ドゥスモン\n住所:ソウル特別市龍山区元暁路2街3-2\n基本説明:予約制で運営される落ち着いた雰囲気のワインバー。 U字型のバーテーブルでゆったりと料理とナチュラルワインを楽しむことができる。 ホタテ貝柱、チャコールグリルドチキン、鴨胸肉ステーキなどカジュアルダイニングができるメニューが多い。\nメニュー:チキンフォアグラパフェ(1万1千ウォン)、ホタテ貝柱(1万6千ウォン)、ビーフタル、ヒラメカルパチオ(各1万8千ウォン)、チャコールグリルドチキン(2万9千ウォン)、ワラビトマトラグパスタ(1万9千ウォン)、鴨の胸肉ステーキ(3万2千ウォン)\n価格帯 : 2~5万ウォン代\n駐車可能可否:不可\nアクセス:孝昌公園前駅 5番出口から三角地駅方向に400メートル直進\n営業時間:18:00~24:00(ラストオーダー22:40)\n特徴:恋人と一緒に行くと良い、お酒飲みやすい、夕方のみ営業する、カウンター席がある",
    "QA": [
        {
            "question": "ドゥスモンはどのエリアにありますか？",
            "answer": "ドゥスモンはソウル特別市龍山区にあります。"
        },
        {
            "question": "ドゥスモンの営業時間は何時から何時までですか？",
            "answer": "ドゥスモンの営業時間は18:00から24:00までです。ラストオーダーは22:40です。"
        },
        {
            "question": "ドゥスモンのメニューにはどんな料理がありますか？",
            "answer": "ドゥスモンのメニューにはチキンフォアグラパフェ、ホタテ貝柱、ビーフタル、ヒラメカルパチオ、チャコールグリルドチキン、ワラビトマトラグパスタ、鴨の胸肉ステーキなどがあります。"
        },
        {
            "question": "ドゥスモンは予約制ですか？",
            "answer": "はい、ドゥスモンは予約制で運営されています。"
        },
        {
            "question": "ドゥスモンは駐車可能ですか？",
            "answer": "いいえ、ドゥスモンでは駐車はできません。"
        },
        {
            "question": "ドゥスモンへのアクセス方法はありますか？",
            "answer": "ドゥスモンへのアクセス方法は、孝昌公園前駅の5番出口から三角地駅方向に400メートル直進することです。"
        }
    ],
    "word_Count": {
        "text": 297,
        "QA": 261
    }
}