{
    "data_info": {
        "documentID": "J_FOOD_021752",
        "source": "도서",
        "writer": "이주영",
        "ISBN_ISNN": "979-11-6050-024-0",
        "version": "초판",
        "source_language": "ko",
        "translator": "파파고",
        "source_url": "나홀로 여행 컨설팅북",
        "collectedDate": "2023-11-01",
        "publishedDate": "2016-11-30",
        "domain": "음식점",
        "title": "피오브프레즐"
    },
    "text": "釜山広域市水営区南川沖路38-81階に位置するプレッツェル専門店ピ・オフ・プレッツェルは当日生産/当日販売を原則としています。 様々なプレッツェルと一緒にブランチメニューも提供しており、オーガニック小麦粉とレスキュアAOP認証バターを使用して良い材料で作ったおいしいプレッツェルを披露します。 常にお客様に良いサービスを提供するために努力します。 駐車は近くの有料駐車場をご利用ください。 場所情報は、金蓮山駅の3番出口から広安里方向にまっすぐ降りていただくとスターバックス南川店の隣の路地に入っていただくと1階に位置しております。 車を利用する際、最寄りの有料駐車場は彦陽プルコギです。 メニューにはネギクリームチーズ(7,500ウォン)、ディープチョコ(5,500ウォン)、ペパロニ(5,300ウォン)、アップルバタークランブル(5,500ウォン)、シナモン(4,300ウォン)、プレーン(3,800ウォン)、トマトスープ(7,000ウォン)、アメリカーノ(5,000ウォン)などがあります。",
    "QA": [
        {
            "question": "プレッツェル専門店ピ・オフ・プレッツェルの場所はどこですか？",
            "answer": "プレッツェル専門店ピ・オフ・プレッツェルは釜山広域市水営区南川沖路38-81階に位置しています。"
        },
        {
            "question": "ピ・オフ・プレッツェルはどのようなメニューを提供していますか？",
            "answer": "ピ・オフ・プレッツェルではネギクリームチーズ、ディープチョコ、ペパロニ、アップルバタークランブル、シナモン、プレーンなどの様々なプレッツェルを提供しています。また、ブランチメニューとしてトマトスープやアメリカーノも取り揃えています。"
        },
        {
            "question": "ピ・オフ・プレッツェルはいつ営業していますか？",
            "answer": "ピ・オフ・プレッツェルは当日生産/当日販売を原則としているため、営業時間は変動します。"
        },
        {
            "question": "ピ・オフ・プレッツェルには駐車場はありますか？",
            "answer": "ピ・オフ・プレッツェルの近くには有料駐車場があります。最寄りの有料駐車場は彦陽プルコギです。"
        },
        {
            "question": "ピ・オフ・プレッツェルの材料はどのように作られていますか？",
            "answer": "ピ・オフ・プレッツェルではオーガニック小麦粉とレスキュアAOP認証バターを使用しています。良い材料で作られたおいしいプレッツェルを提供しています。"
        }
    ],
    "word_Count": {
        "text": 328,
        "QA": 338
    }
}