{
    "data_info": {
        "documentID": "J_HIS_039180",
        "source": "온라인문서",
        "writer": "null",
        "ISBN_ISNN": "null",
        "version": "null",
        "source_language": "ko",
        "translator": "파파고",
        "source_url": "'https://www.heritage.go.kr/heri/cul/culSelectDetail.do?culPageNo=92&region=1&searchCondition=&searchCondition2=&s_kdcdArr=&s_ctcdArr=&ccbaPcd1Arr=&ccbaKdcd=12&ccbaAsno=07180000&ccbaCtcd=35&ccbaCpno=1123507180000&ccbaCndt=&ccbaLcto=&stCcbaAsno=&endCcbaAsno=&stCcbaAsdt=&endCcbaAsdt=&chGubun=&header=view&returnUrl=%2fheri%2fcul%2fculSelectViewList.do&pageNo=1_1_2_0&sngl=Y",
        "collectedDate": "2023-11-03",
        "publishedDate": "1981-03-18",
        "domain": "문화/역사관광",
        "title": "전주이씨 고림군파 종중 문서 일괄"
    },
    "text": "全州李氏高林君派宗中文書一括 (전주이씨 고림군파 종중 문서 일괄)\\n\n全北 全州市 完山区 よもぎ峠へ 249、国立チョンジュ(全州)博物館 (孝子洞(ヒョジャドン)2街、国立チョンジュ(全州)博物館)\\n\n朝鮮燕山君8年(1502)、宝物、全州李氏高林郡派宗中文書一括は朝鮮燕山郡8年(1502)から宣祖26年(1593)までの古文書4枚だ。 財産を分ける文書である許汝文基（ホ·ヨムンギ、1502）1枚と財産主が亡くなった後、彼の子供たちが集まって合意して財産を分けた文書である同福和会文基（1528）1枚、同福和会入議（文禄·慶長の役以前）1枚、同福和会成文（1593）1枚などだ。 これらは太宗の次男孝寧大君の孫である高林郡李訓とその息子七山郡先孫の二大間で財産を相続し、子供たちに分配した内容が盛り込まれた文書だ。 ホ·ヨムンギとドンボクファフェムンギは高林郡イ·フンが彼の息子チルサン郡に譲与した文書であり、ドンボクファフェ入議とドンボクファフェソンムンはチルサン郡が彼の実の兄弟姉妹との合意を通じて彼らに財産を分配した文書だ。 朝鮮時代の王室内での財産相続に関する研究と経済史研究において貴重な資料と評価される。",
    "QA": [
        {
            "question": "全州李氏高林郡派宗中文書一括は何時から何時までの古文書ですか？",
            "answer": "朝鮮燕山郡8年(1502)から宣祖26年(1593)までの古文書です。"
        },
        {
            "question": "全州李氏高林郡派宗中文書一括は何枚の古文書で構成されていますか？",
            "answer": "全州李氏高林郡派宗中文書一括は4枚の古文書で構成されています。"
        },
        {
            "question": "この文書の内容は何ですか？",
            "answer": "財産を分ける文書であり、財産の相続と分配に関する内容が盛り込まれています。"
        },
        {
            "question": "これらの文書はどのような研究や評価に役立つのですか？",
            "answer": "これらの文書は、朝鮮時代の王室内での財産相続に関する研究と経済史研究において貴重な資料と評価されています。"
        }
    ],
    "word_Count": {
        "text": 378,
        "QA": 189
    }
}