{
    "data_info": {
        "documentID": "J_HIS_044218",
        "source": "온라인문서",
        "writer": "null",
        "ISBN_ISNN": "null",
        "version": "null",
        "source_language": "ko",
        "translator": "파파고",
        "source_url": "'https://www.doopedia.co.kr/",
        "collectedDate": "2023-10-11",
        "publishedDate": "2020-01-01",
        "domain": "문화/역사관광",
        "title": "거창 구연서원 관수루"
    },
    "text": "居昌区淵書院貫首楼\\n\n慶尚南道居昌郡渭川面銀河里キル100(黄山里)\\n\n朝鮮中期の文人のソンペンニョン(成彭年1540~1594)と新水(愼守彛)、新札(愼權)の学徳を称えるため、士林らが建てた口演書院(龜淵書院)の門楼に、2005年1月13日、慶尚南道有形文化財に指定された。旧縁書院はもともとクヨンジェとしたが、1694年口演書院と改称され、1868年大院君(テウォングン)の書院フェチョルリョンにより焼失されたが、門樓であるグヮンスルと講堂は今まで残っている。1740年(英祖16)建築されたグヮンスル(觀水樓)は正面3間・側面2間の重層楼閣の建物に二重の軒の入母屋屋根の建物だ。自然岩盤を活用して、ずれた材木を下部柱で使用するなど、自然との調和を成している建築物で形もまたとても美しい。岩盤の間に造成された基壇の上に自然石の礎石を置いて柱を立て、柱は円柱で、柱の外側の四隅には適切に高さを調節した滑走を立てた。楼閣の下の階に出入り口をつけて残りの空間は全て開放しており、上の階の床には格子模様の床を敷いて界磁の欄干をぐるっと巻いた。自然との調和という韓国建築の最も大きな特徴をよく示して、楼建築の模範と言えるほどの比例が優れており、学術的価値が高く、保存上態度良好だ。",
    "QA": [
        {
            "question": "この書院はどのようにして建てられましたか？",
            "answer": "この書院は、士林たちがソンペンニョンや新水、新札の学徳を称えるために建てられました。"
        },
        {
            "question": "この書院の門楼は何のために建てられましたか？",
            "answer": "この書院の門楼は、口演書院の門として建てられ、学問の場としての重要性を示しています。"
        },
        {
            "question": "この書院の門楼は何年に指定されましたか？",
            "answer": "この書院の門楼は、2005年1月13日に慶尚南道有形文化財に指定されました。"
        },
        {
            "question": "この書院の門楼はどのような特徴がありますか？",
            "answer": "この書院の門楼は、自然岩盤を活用して建てられ、美しい形状と自然との調和を成しています。"
        },
        {
            "question": "この書院の門楼はどのようにして建築されましたか？",
            "answer": "この書院の門楼は、岩盤の間に造成された基壇の上に自然石の礎石を置いて柱を立て、柱は円柱で、柱の外側の四隅には適切に高さを調節した滑走を立てました。"
        },
        {
            "question": "この書院の門楼はどのような価値がありますか？",
            "answer": "この書院の門楼は、韓国建築の最も大きな特徴である自然との調和を示しており、学術的価値が高く、保存状態も良好です。"
        }
    ],
    "word_Count": {
        "text": 396,
        "QA": 311
    }
}