{
    "data_info": {
        "documentID": "J_HIS_079683",
        "source": "온라인문서",
        "writer": null,
        "ISBN_ISNN": null,
        "version": null,
        "source_language": "ko",
        "translator": "파파고",
        "source_url": "'https://www.doopedia.co.kr/",
        "collectedDate": "2023-10-11",
        "publishedDate": "2023-10-11",
        "domain": "문화/역사관광",
        "title": "삼충사_1"
    },
    "text": "三虫舎\\n\n忠清南道扶余郡扶余邑双北里40-1番地\\n\n1984年5月17日、忠清南道の文化財資料に指定された。百済の忠臣である成虫(成忠:?∼656)、興首(興首:?∼?)、階伯(階伯:?∼660)の忠節を称えるために立てられた祠である。1957年に立て、1981年に再建した。毎年10月、百済文化祭の際に、ここでサムチュン制(三忠祭)を務めている。",
    "QA": [
        {
            "question": "この祠が建てられた年はいつですか？",
            "answer": "1984年5月17日"
        },
        {
            "question": "この祠が指定された文化財資料はどこですか？",
            "answer": "忠清南道"
        },
        {
            "question": "この祠が誰を称えるために立てられたのですか？",
            "answer": "百済の忠臣である成虫、興首、階伯の忠節を称えるために立てられました。"
        },
        {
            "question": "この祠が再建された年はいつですか？",
            "answer": "1981年"
        },
        {
            "question": "毎年10月に何が行われるのですか？",
            "answer": "毎年10月、百済文化祭の際に、ここでサムチュン制(三忠祭)を務めています。"
        }
    ],
    "word_Count": {
        "text": 129,
        "QA": 134
    }
}