{
    "data_info": {
        "documentID": "J_HIS_060039",
        "source": "온라인문서",
        "writer": "null",
        "ISBN_ISNN": "null",
        "version": "null",
        "source_language": "ko",
        "translator": "파파고",
        "source_url": "'https://www.museum.go.kr/site/main/relic/search/view?relicId=370",
        "collectedDate": "2023-10-11",
        "publishedDate": "2020-01-01",
        "domain": "문화/역사관광",
        "title": "대당평일백제비 탑본"
    },
    "text": "大唐平日白ツバメの塔本 (대당평일백제비 탑본)\\n\nこの拓本は、紀元660年に唐が新羅武烈王7年により百済を滅ぼした際の出来事を記録した文の拓本です。オリジナルの碑は、5層からなる石塔の第1階に、南側から時計回りに4面ずつ合計16面にわたり、文字が刻まれています。この塔碑は、唐と新羅が協力し百済を攻撃し、泗沘城を陥落させ、百済の王と臣下を捕虜にした出来事などを記録しています。また、百済の旧首都である定林寺の中央に位置しており、百済の終焉を象徴しています。この拓本は、百済の崩壊後の時代の雰囲気や旧百済都の状況を物語っています。国籍/時代：韓国、材質：紙、分類：文化芸術-書画-拓本-碑文です。",
    "QA": [
        {
            "question": "この拓本は何を記録しているのですか？",
            "answer": "この拓本は、紀元660年に唐が新羅武烈王7年により百済を滅ぼした際の出来事を記録した文の拓本です。"
        },
        {
            "question": "オリジナルの塔碑はどのような形状ですか？",
            "answer": "オリジナルの塔碑は5層からなる石塔で、南側から時計回りに4面ずつ合計16面にわたり、文字が刻まれています。"
        },
        {
            "question": "この塔碑はどのような出来事を記録していますか？",
            "answer": "この塔碑は、唐と新羅が協力し百済を攻撃し、泗沘城を陥落させ、百済の王と臣下を捕虜にした出来事などを記録しています。"
        },
        {
            "question": "この拓本はどのような意味を持っていますか？",
            "answer": "この拓本は、百済の旧首都である定林寺の中央に位置しており、百済の終焉を象徴しています。また、百済の崩壊後の時代の雰囲気や旧百済都の状況を物語っています。"
        },
        {
            "question": "この拓本の国籍と時代は何ですか？",
            "answer": "この拓本は韓国の作品であり、紀元660年の時代に作成されました。"
        },
        {
            "question": "この拓本の材質は何ですか？",
            "answer": "この拓本の材質は紙です。"
        },
        {
            "question": "この拓本はどのような分類に属していますか？",
            "answer": "この拓本は文化芸術の分類で、書画の一種である拓本の碑文です。"
        }
    ],
    "word_Count": {
        "text": 219,
        "QA": 323
    }
}