{
    "data_info": {
        "documentID": "J_HIS_016715",
        "source": "온라인문서",
        "writer": "null",
        "ISBN_ISNN": "null",
        "version": "null",
        "source_language": "ja",
        "translator": "null",
        "source_url": "'https://trippose.com/festival/muchangpo-mystic-sea-road-festival",
        "collectedDate": "2023-10-04",
        "publishedDate": "2020-01-01",
        "domain": "문화/역사관광",
        "title": "武昌浦 神秘の海割れ祭り"
    },
    "text": "武昌浦 神秘の海割れ祭り\\n\n忠清南道 保寧市 熊川邑 ヨルリンパダ1キル 10\\n\n第16回武昌浦神秘の海割れ祭りが2015年8月14日（金）から忠清南道保寧市の武昌浦海水浴場で開催されます。このお祭りは、潮が引くと武昌浦の浜辺から石台島までの約1.5キロに道が現れ「現代版モーゼの奇跡」と人気を集め毎陰暦15日と大晦日の干潮に合わせて開催されています。芸能人の公演、たいまつ漁業体験など様々な見どころと、魚手づかみ体験、潮干狩り体験、マテ貝の身釣り体験など多くの体験イベントが味わえます。",
    "QA": [
        {
            "question": "武昌浦神秘の海割れ祭りはいつ開催されますか？",
            "answer": "武昌浦神秘の海割れ祭りは2015年8月14日（金）から開催されます。"
        },
        {
            "question": "武昌浦神秘の海割れ祭りはどこで開催されますか？",
            "answer": "武昌浦神秘の海割れ祭りは忠清南道保寧市の武昌浦海水浴場で開催されます。"
        },
        {
            "question": "武昌浦神秘の海割れ祭りの見どころは何ですか？",
            "answer": "武昌浦神秘の海割れ祭りでは、芸能人の公演やたいまつ漁業体験など様々な見どころがあります。また、魚手づかみ体験や潮干狩り体験、マテ貝の身釣り体験など多くの体験イベントも楽しめます。"
        },
        {
            "question": "武昌浦神秘の海割れ祭りはいつ開催されますか？",
            "answer": "武昌浦神秘の海割れ祭りは毎陰暦15日と大晦日の干潮に合わせて開催されています。"
        }
    ],
    "word_Count": {
        "text": 180,
        "QA": 209
    }
}