{
    "data_info": {
        "documentID": "J_NAT_035525",
        "source": "온라인문서",
        "writer": "null",
        "ISBN_ISNN": "null",
        "version": "null",
        "source_language": "ko",
        "translator": "파파고",
        "source_url": "'https://encykorea.aks.ac.kr/Article/E0028635",
        "collectedDate": "2023-09-20",
        "publishedDate": "2020-01-01",
        "domain": "자연관광",
        "title": "선국사(善國寺)"
    },
    "text": "全羅北道南原市には南北国時代に創建された寺院である金山寺(金山寺)のマルサインサンソンジョルがある。この寺院は大韓仏教曹渓宗第17教区本寺と、金山寺は685年に設立されたことが知られている。金山寺はソングクサに名前が変更されており、蛟竜山城内に位置して軍本部に使用されており、全盛期には300人余りの僧侶があった。ドンハクラン時には東学軍がここを占領し、査察の建物とヒートアイランド入りの瓶が破壊された。1917年には大雄殿が改修されたが、この建物は玄岩(玄巖)によって建てられたものだ。現在お寺にはソングクサ、大雄殿だけでなく、チルソンガク、寮舎棟、ボーゼルなどがあり、対北朝鮮と蛟竜山城スンジャン同人の印鑑も、文化財に指定されている。この寺の周囲では真相鶏、初動コメ、細動コメ、グヮンワンミョのセリなどが生産されており、酸性飴はサンゴクリの特産物として知られている。",
    "QA": [
        {
            "question": "金山寺はいつ創建されましたか？",
            "answer": "金山寺は685年に創建されました。"
        },
        {
            "question": "金山寺は何教区の本寺ですか？",
            "answer": "金山寺は大韓仏教曹渓宗第17教区の本寺です。"
        },
        {
            "question": "金山寺の全盛期には何人程の僧侶がいたのですか？",
            "answer": "金山寺の全盛期には300人余りの僧侶がいました。"
        },
        {
            "question": "金山寺の周囲ではどのような特産物がありますか？",
            "answer": "金山寺の周囲では真相鶏、初動コメ、細動コメ、グヮンワンミョのセリなどの特産物があります。"
        },
        {
            "question": "金山寺の現在の建物には何が含まれていますか？",
            "answer": "金山寺の現在の建物にはソングクサ、大雄殿、チルソンガク、寮舎棟、ボーゼルなどが含まれています。"
        },
        {
            "question": "金山寺の文化財に指定されているものは何ですか？",
            "answer": "金山寺の文化財に指定されているものには、対北朝鮮と蛟竜山城スンジャン同人の印鑑が含まれています。"
        }
    ],
    "word_Count": {
        "text": 282,
        "QA": 236
    }
}