{
    "data_info": {
        "documentID": "J_NAT_004372",
        "source": "도서",
        "writer": "손만기",
        "ISBN_ISNN": "978-89-98417-43-7 (14980)",
        "version": "개정3판",
        "source_language": "ko",
        "translator": "파파고",
        "source_url": "대한민국 여행자를 위한, 제주도 여행백서",
        "collectedDate": "2023-10-25",
        "publishedDate": "2019-04-10",
        "domain": "자연관광",
        "title": "가파도 (3)"
    },
    "text": "加波島は済州道で風がたくさん吹くことで有名なところとして知られている。 この島は高度が低く、遠い海から吹いてくる風を見分けることができないからだ。 加波島を旅行するのに良い時期は春として青麦が風に踊る季節だ。 島全体の70%が青麦で覆われているが、毎年4~5月には加波島青麦祭りが開かれることもある。 加波島を旅行する時は時間と方向に塗炭しなくても良い。 この島ではどこでも漢拏山と馬羅島を見ることができるが、漢拏山と馬羅島さえ見つければすぐ方向が分かる。 そのため加波島を旅行しながら心を低くすることができる。 自然が贈り物をすることを期待するのも良い方法だろう。",
    "QA": [
        {
            "question": "加波島とはどんな場所ですか？",
            "answer": "加波島は済州道で風がたくさん吹くことで有名な島です。"
        },
        {
            "question": "加波島を旅行するのにおすすめの時期はいつですか？",
            "answer": "加波島を旅行するのにおすすめの時期は春です。"
        },
        {
            "question": "加波島青麦祭りはいつ開催されますか？",
            "answer": "加波島青麦祭りは毎年4~5月に開催されます。"
        },
        {
            "question": "加波島での風の方向はどうやって分かりますか？",
            "answer": "加波島では漢拏山と馬羅島を見つければすぐ方向が分かります。"
        },
        {
            "question": "加波島で自然の贈り物を期待することはありますか？",
            "answer": "加波島では自然が贈り物をすることを期待することができます。"
        }
    ],
    "word_Count": {
        "text": 207,
        "QA": 168
    }
}