{
    "data_info": {
        "documentID": "J_NAT_017290",
        "source": "도서",
        "writer": "이종원",
        "ISBN_ISNN": "978-89-94799-23-0 (13980)",
        "version": "초판15쇄",
        "source_language": "ko",
        "translator": "파파고",
        "source_url": "대한민국 숨겨진 여행지 100",
        "collectedDate": "2023-10-24",
        "publishedDate": "2020-10-20",
        "domain": "자연관광",
        "title": "태안 해수욕장 순례5"
    },
    "text": "泰安海水浴場は北西に向かっており、冬には北西季節風を直接迎える。 長い歳月と風が小さな砂を積んで少しずつ積み上げて巨大な丘を作り出した。 風の方向によって丘の位置と大きさが随時変わるが、ここでは砂丘、砂丘湿地、砂丘林地などすべての自然条件を見ることができる。 子供たちには良い生態コースとして人気が高い。",
    "QA": [
        {
            "question": "泰安海水浴場はどの方向に向かっていますか？",
            "answer": "泰安海水浴場は北西に向かっています。"
        },
        {
            "question": "泰安海水浴場では何が見ることができますか？",
            "answer": "泰安海水浴場では砂丘、砂丘湿地、砂丘林地などすべての自然条件を見ることができます。"
        },
        {
            "question": "冬に泰安海水浴場では何が起こりますか？",
            "answer": "冬には北西季節風を直接迎えるため、風が小さな砂を積んで巨大な丘を作り出します。"
        },
        {
            "question": "なぜ泰安海水浴場は砂丘がありますか？",
            "answer": "長い歳月と風が小さな砂を積んで少しずつ積み上げて巨大な丘を作り出したためです。"
        },
        {
            "question": "泰安海水浴場は子供たちに人気がありますか？",
            "answer": "はい、泰安海水浴場は子供たちにとって良い生態コースとして人気が高いです。"
        }
    ],
    "word_Count": {
        "text": 111,
        "QA": 200
    }
}