{
    "data_info": {
        "documentID": "J_NAT_005679",
        "source": "온라인문서",
        "writer": "null",
        "ISBN_ISNN": "null",
        "version": "null",
        "source_language": "ko",
        "translator": "파파고",
        "source_url": "'https://www.heritage.go.kr/heri/cul/culSelectDetail.do?culPageNo=285&region=1&searchCondition=&searchCondition2=&s_kdcdArr=&s_ctcdArr=&ccbaPcd1Arr=&ccbaKdcd=15&ccbaAsno=01310000&ccbaCtcd=31&ccbaCpno=1353101310000&ccbaCndt=&ccbaLcto=&stCcbaAsno=&endCcbaAsno=&stCcbaAsdt=&endCcbaAsdt=&chGubun=&header=view&returnUrl=%2fheri%2fcul%2fculSelectViewList.do&pageNo=1_1_2_0&sngl=Y",
        "collectedDate": "2023-11-03",
        "publishedDate": "2022-01-12",
        "domain": "자연관광",
        "title": "관동대로 구질현"
    },
    "text": "関東大路九質県 (관동대로 구질현)\\n\n京畿道楊平郡\\n\n- , 名勝 , 関東大路九質県は江原道から首都圏、漢陽に向かう関東大路の一部で、『新増』に「九質県」と記録されている。道沿いに鬱蒼とした樹林が茂り美しい景観を形成しており、南漢江水運を利用するために通らなければならない街角であり、歴史的価値も大きい昔の道である",
    "QA": [
        {
            "question": "関東大路九質県はどこに位置していますか？",
            "answer": "関東大路九質県は江原道から首都圏、漢陽に向かう関東大路の一部です。"
        },
        {
            "question": "関東大路九質県はどのような景観が広がっていますか？",
            "answer": "関東大路九質県は鬱蒼とした樹林が茂り美しい景観を形成しています。"
        },
        {
            "question": "なぜ関東大路九質県は歴史的価値があると言われていますか？",
            "answer": "関東大路九質県は南漢江水運を利用するために通らなければならない街角であり、歴史的価値があります。"
        },
        {
            "question": "関東大路九質県はどのような目的で使われていましたか？",
            "answer": "関東大路九質県は南漢江水運を利用するために使われていました。"
        },
        {
            "question": "関東大路九質県は何と呼ばれていますか？",
            "answer": "関東大路九質県と呼ばれています。"
        }
    ],
    "word_Count": {
        "text": 118,
        "QA": 203
    }
}