{
    "data_info": {
        "documentID": "J_STAY_063466",
        "source": "온라인문서",
        "writer": "null",
        "ISBN_ISNN": "null",
        "version": "null",
        "source_language": "ko",
        "translator": "파파고",
        "source_url": "'https://myrealtrip.com/accommodations/stays/1081887?place[place_type]=GID&place[gid]=1081887&place[latitude]=37.5406839207&place[longitude]=126.9483610352&checkin=2023-12-03&checkout=2023-12-04&adult_count=1&curation_type=ALL",
        "collectedDate": "2023-11-14",
        "publishedDate": "2020-01-01",
        "domain": "숙박",
        "title": "베스트웨스턴 프리미어 서울가든"
    },
    "text": "付帯施設としてはLa Stellaビュッフェ、カフェ1883、フィットネスセンターがあります。 朝食はh''_Gardenビュッフェで提供され、月~金は07:00~09:30、土~日は07:00~10:00までです。 大人は32,000ウォン、小人は(48ヶ月~12歳)16,000ウォンで、当日現地にてお支払いいただけます。 宿泊客の特典としてはフィットネスセンターのご利用が無料で、ベビーベッドも無料です。 しかし、それ以外の事項はありません。 チェックインは15:00で、チェックアウトは12:00です。 無料Wi-Fiが提供され、すべての客室は禁煙です。 Bath Amenityの歯磨き粉と歯ブラシは有料で、個人金庫もご利用いただけます。 駐車は1台当たり1泊当たり3,000ウォンの有料です。 客室内では全客室人数の追加が不可能であり、エキストラベッドを追加利用しようとする場合には現場追加時44,000ウォン、事前予約時33,000ウォンの費用がかかります。 客室情報にはスタンダードツイン、スタンダードダブル、スーペリアツイン、スーペリアダブルなどのタイプがあり、基準はすべて2名様で最大人数も2名様です。 [朝食2人+高層割り当て] スーペリアツイン、スーペリアダブルの場合は高層に割り当てられ、朝食が含まれます。 また、最大人数を超える場合は入室できず、未成年者は保護者同伴なしでは利用できません。 チェックインの際に割り当て商品またはベッドタイプが記載されていない場合は、特定の客室とベッドタイプを保証しません。 客室価格は税金とサービス料が含まれた金額です。",
    "QA": [
        {
            "question": "朝食は何時から何時までですか？",
            "answer": "月曜日から金曜日は07:00~09:30、土曜日と日曜日は07:00~10:00です。"
        },
        {
            "question": "朝食の料金はいくらですか？",
            "answer": "大人は32,000ウォン、小人(48ヶ月~12歳)は16,000ウォンです。"
        },
        {
            "question": "フィットネスセンターの利用料金はいくらですか？",
            "answer": "宿泊客は無料で利用できます。"
        },
        {
            "question": "チェックインの時間は何時ですか？",
            "answer": "チェックインは15:00です。"
        },
        {
            "question": "チェックアウトの時間は何時ですか？",
            "answer": "チェックアウトは12:00です。"
        },
        {
            "question": "客室内で利用できるアメニティについて教えてください。",
            "answer": "客室内では有料の歯磨き粉と歯ブラシが利用可能で、個人金庫もご利用いただけます。"
        },
        {
            "question": "駐車場の料金はいくらですか？",
            "answer": "1泊あたり1台につき3,000ウォンです。"
        },
        {
            "question": "客室にエキストラベッドを追加できますか？",
            "answer": "客室内では全客室人数の追加が不可能であり、エキストラベッドを追加しようとする場合には追加時44,000ウォン、事前予約時33,000ウォンの費用がかかります。"
        }
    ],
    "word_Count": {
        "text": 506,
        "QA": 299
    }
}