{
    "data_info": {
        "documentID": "J_STAY_065835",
        "source": "온라인문서",
        "writer": "null",
        "ISBN_ISNN": "null",
        "version": "null",
        "source_language": "ko",
        "translator": "파파고",
        "source_url": "'https://myrealtrip.com/accommodations/stays/2663781?place[place_type]=GID&place[gid]=2663781&place[latitude]=35.9157634832&place[longitude]=129.1494792599&checkin=2023-12-03&checkout=2023-12-04&adult_count=1&curation_type=ALL",
        "collectedDate": "2023-11-14",
        "publishedDate": "2020-01-01",
        "domain": "숙박",
        "title": "경주 캠핑573"
    },
    "text": "キャンプニックは入室基準で3時間で、17:30から20:30までご利用いただけます。 宿泊商品は提供されず、3時間分の席のレンタル商品です。 追加人数を追加する場合、1人当たり10,000ウォンの費用が発生し、現場決済で行われます。 入室は15:00から可能で、退室は11:00までです。 送迎サービスは提供しておりません。 客室内では炭グリルが利用でき、価格は1部屋当たり20,000ウォンです。 キャンプニック肉のセットメニューには、肩ロース500g、海老、手作りソーセージ、きのこ、レトルトご飯2個(ラーメン2個)が含まれており、利用時間は3時間です。 価格は46,000ウォンで2名基準であり、事前予約が必須です。 幼児の基準に基づいて現場決済が行われ、最大人数を超えることはできません。 宿泊施設としてはグランピングが提供され、客室内で調理が可能です。 愛犬は入室できませんし、駐車場は無料でご利用いただけます。 ただし、現場の状況によってはご利用いただけない場合がございます。 消火器、電気、流し台も備えられています。 売店は10時から22時まで利用でき、小さな図書館も無料で利用できます。 ミルキットは肉類(トマホッグ、ドンマホック、ポークリブ、サムギョプサルなどバーベキュー用)として販売され、利用時間は22:00までです。 共用トイレやシャワールームも利用でき、タオルやヘアドライヤーは個別に持参してください。 ご利用時間はチェックイン時間の15:00からチェックアウト時間の11:00までです。 客室情報はキャンプニック、カンジャガル、そしてグランピングで構成され、それぞれの基準人数と最大人数があります。",
    "QA": [
        {
            "question": "キャンプニックの利用時間は何時から何時までですか？",
            "answer": "キャンプニックの利用時間は17:30から20:30までです。"
        },
        {
            "question": "キャンプニック肉のセットメニューには何が含まれていますか？",
            "answer": "キャンプニック肉のセットメニューには肩ロース500g、海老、手作りソーセージ、きのこ、レトルトご飯2個(ラーメン2個)が含まれています。"
        },
        {
            "question": "キャンプニックの追加人数料金はいくらですか？",
            "answer": "キャンプニックの追加人数料金は1人当たり10,000ウォンです。"
        },
        {
            "question": "グランピングの客室内で利用できる調理器具は何ですか？",
            "answer": "グランピングの客室内では炭グリルが利用できます。価格は1部屋当たり20,000ウォンです。"
        },
        {
            "question": "売店の利用可能時間帯は何時から何時までですか？",
            "answer": "売店は10時から22時まで利用できます。"
        }
    ],
    "word_Count": {
        "text": 522,
        "QA": 234
    }
}